setup.py
placescraper/__init__.py
placescraper/base.py
placescraper/version.py
placescraper.egg-info/PKG-INFO
placescraper.egg-info/SOURCES.txt
placescraper.egg-info/dependency_links.txt
placescraper.egg-info/not-zip-safe
placescraper.egg-info/requires.txt
placescraper.egg-info/top_level.txt