Metadata-Version: 1.1
Name: placescraper
Version: 0.1
Summary: A websockets scraper for /r/place on reddit
Home-page: https://github.com/PlaceDevs/place-scraper
Author: teaearlgraycold
Author-email: UNKNOWN
License: MIT
Platform: UNKNOWN
Classifier: Development Status :: 3 - Alpha
Classifier: Environment :: Console
Classifier: Intended Audience :: Developers
Classifier: License :: OSI Approved :: MIT License
Classifier: Programming Language :: Python :: 3.6
Classifier: Programming Language :: Python :: Implementation :: CPython
Classifier: Topic :: Utilities
